{
  "type": "FeatureCollection",
  "features": [
    {
      "type": "Feature",
      "properties": {},
      "geometry": {
        "coordinates": [
          [
            [
              -180.9881088009222,
              71.35453696007684
            ],
            [
              -180.9881088009222,
              15.276552218371137
            ],
            [
              -61.10529630092191,
              15.276552218371137
            ],
            [
              -61.10529630092191,
              71.35453696007684
            ],
            [
              -180.9881088009222,
              71.35453696007684
            ]
          ]
        ],
        "type": "Polygon"
      }
    }
  ]
}